python_testing_advanced/__init__.py
python_testing_advanced/python_testing_advanced.py
python_testing_advanced-0.3.6.dist-info/METADATA
python_testing_advanced-0.3.6.dist-info/RECORD
python_testing_advanced-0.3.6.dist-info/WHEEL
python_testing_advanced-0.3.6.dist-info/top_level.txt
