Metadata-Version: 2.1
Name: python-testing-advanced
Version: 0.3.6
Summary: Python Testing Advanced
Home-page: https://github.com/jatap/python_testing_advanced
Author: Julio Antúnez Tarín
Author-email: julio.antunez.tarin@gmail.com
License: MIT license
Keywords: python_testing_advanced
Platform: UNKNOWN
Classifier: Development Status :: 2 - Pre-Alpha
Classifier: Intended Audience :: Developers
Classifier: License :: OSI Approved :: MIT License
Classifier: Natural Language :: English
Classifier: Programming Language :: Python :: 2
Classifier: Programming Language :: Python :: 2.7
Classifier: Programming Language :: Python :: 3
Classifier: Programming Language :: Python :: 3.4
Classifier: Programming Language :: Python :: 3.5
Classifier: Programming Language :: Python :: 3.6
Classifier: Programming Language :: Python :: 3.7
